{"version":"1.1.2","tokens":"3046ac8a5c8b7dd45cf3c6edfd60c1e383c8a0bc3aab8de7d3db4881119a2cdf","gitInfo":{"name":"wnews-nuxt","owner":"wnews","url":"https://github.com/wnews/wnews-nuxt"},"contentSchema":{},"appConfigSchema":{"properties":{"id":"#appConfig","properties":{"nuxtIcon":{"title":"Nuxt Icon","description":"Configure Nuxt Icon module preferences.","id":"#appConfig/nuxtIcon","properties":{"size":{"title":"Icon Size","description":"Set the default icon size. Set to false to disable the sizing of icon in style.","tags":["@studioIcon material-symbols:format-size-rounded"],"tsType":"string | false","id":"#appConfig/nuxtIcon/size","default":"1em","type":"string"},"class":{"title":"CSS Class","description":"Set the default CSS class.","tags":["@studioIcon material-symbols:css"],"id":"#appConfig/nuxtIcon/class","default":"","type":"string"},"aliases":{"title":"Icon aliases","description":"Define Icon aliases to update them easily without code changes.","tags":["@studioIcon material-symbols:star-rounded"],"tsType":"{ [alias: string]: string }","id":"#appConfig/nuxtIcon/aliases","default":{},"type":"object"},"iconifyApiOptions":{"title":"Iconify API Options","description":"Define preferences for Iconify API fetch.","tags":["@studioIcon material-symbols:tv-options-input-settings"],"id":"#appConfig/nuxtIcon/iconifyApiOptions","properties":{"url":{"title":"Iconify API URL","description":"Define a custom Iconify API URL. Useful if you want to use a self-hosted Iconify API. Learn more: https://iconify.design/docs/api.","tags":["@studioIcon material-symbols:api"],"id":"#appConfig/nuxtIcon/iconifyApiOptions/url","default":"https://api.iconify.design","type":"string"},"publicApiFallback":{"title":"Public Iconify API fallback","description":"Define if the public Iconify API should be used as fallback.","tags":["@studioIcon material-symbols:public"],"id":"#appConfig/nuxtIcon/iconifyApiOptions/publicApiFallback","default":false,"type":"boolean"}},"type":"object","default":{"url":"https://api.iconify.design","publicApiFallback":false}}},"type":"object","default":{"size":"1em","class":"","aliases":{},"iconifyApiOptions":{"url":"https://api.iconify.design","publicApiFallback":false}}},"ui":{"title":"UI","description":"UI Customization.","tags":["@studioIcon i-mdi-palette-outline"],"id":"#appConfig/ui","properties":{"icons":{"title":"Icons","description":"Manage icons used in UI Pro.","tags":["@studioIcon i-mdi-application-settings-outline"],"id":"#appConfig/ui/icons","properties":{"search":{"type":"string","title":"Search Bar","description":"Icon to display in the search bar.","default":"i-heroicons-magnifying-glass-20-solid","tags":["@studioInput icon","@studioIcon i-mdi-magnify"],"id":"#appConfig/ui/icons/search"},"dark":{"type":"string","title":"Dark mode","description":"Icon of color mode button for dark mode.","default":"i-heroicons-moon-20-solid","tags":["@studioInput icon","@studioIcon i-mdi-moon-waning-crescent"],"id":"#appConfig/ui/icons/dark"},"light":{"type":"string","title":"Light mode","description":"Icon of color mode button for light mode.","default":"i-heroicons-sun-20-solid","tags":["@studioInput icon","@studioIcon i-mdi-white-balance-sunny"],"id":"#appConfig/ui/icons/light"},"external":{"type":"string","title":"External Link","description":"Icon for external link.","default":"i-heroicons-arrow-up-right-20-solid","tags":["@studioInput icon","@studioIcon i-mdi-arrow-top-right"],"id":"#appConfig/ui/icons/external"},"chevron":{"type":"string","title":"Chevron","description":"Icon for chevron.","default":"i-heroicons-chevron-down-20-solid","tags":["@studioInput icon","@studioIcon i-mdi-chevron-down"],"id":"#appConfig/ui/icons/chevron"},"hash":{"type":"string","title":"Hash","description":"Icon for hash anchors.","default":"i-heroicons-hashtag-20-solid","tags":["@studioInput icon","@studioIcon i-ph-hash"],"id":"#appConfig/ui/icons/hash"}},"type":"object","default":{"search":"i-heroicons-magnifying-glass-20-solid","dark":"i-heroicons-moon-20-solid","light":"i-heroicons-sun-20-solid","external":"i-heroicons-arrow-up-right-20-solid","chevron":"i-heroicons-chevron-down-20-solid","hash":"i-heroicons-hashtag-20-solid"}},"primary":{"type":"string","title":"Primary","description":"Primary color of your UI.","default":"green","required":["sky","mint","rose","amber","violet","emerald","fuchsia","indigo","lime","orange","pink","purple","red","teal","yellow","green","blue","cyan","gray","white","black"],"tags":["@studioInput string","@studioIcon i-mdi-palette-outline"],"id":"#appConfig/ui/primary"},"gray":{"type":"string","title":"Gray","description":"Gray color of your UI.","default":"slate","required":["slate","cool","zinc","neutral","stone"],"tags":["@studioInput string","@studioIcon i-mdi-palette-outline"],"id":"#appConfig/ui/gray"}},"type":"object","default":{"icons":{"search":"i-heroicons-magnifying-glass-20-solid","dark":"i-heroicons-moon-20-solid","light":"i-heroicons-sun-20-solid","external":"i-heroicons-arrow-up-right-20-solid","chevron":"i-heroicons-chevron-down-20-solid","hash":"i-heroicons-hashtag-20-solid"},"primary":"green","gray":"slate"}},"seo":{"title":"SEO","description":"SEO configuration.","tags":["@studioIcon i-ph-app-window"],"id":"#appConfig/seo","properties":{"siteName":{"type":"string","title":"Site Name","description":"Name used in ogSiteName and used as second part of your page title (My page title - Nuxt UI Pro).","default":[],"tags":["@studioInput string","@studioIcon i-mdi-web"],"id":"#appConfig/seo/siteName"}},"type":"object","default":{"siteName":[]}},"header":{"title":"Header","description":"Header configuration.","tags":["@studioIcon i-mdi-page-layout-header"],"id":"#appConfig/header","properties":{"logo":{"title":"Logo","description":"Header logo configuration.","tags":["@studioIcon i-mdi-image-filter-center-focus-strong-outline"],"id":"#appConfig/header/logo","properties":{"light":{"type":"string","title":"Light Mode Logo","description":"Pick an image from your gallery.","default":"","tags":["@studioInput media","@studioIcon i-mdi-white-balance-sunny"],"id":"#appConfig/header/logo/light"},"dark":{"type":"string","title":"Dark Mode Logo","description":"Pick an image from your gallery.","default":"","tags":["@studioInput media","@studioIcon i-mdi-moon-waning-crescent"],"id":"#appConfig/header/logo/dark"},"alt":{"type":"string","title":"Alt","description":"Alt to display for accessibility.","default":"","tags":["@studioInput string","@studioIcon i-mdi-alphabet-latin"],"id":"#appConfig/header/logo/alt"}},"type":"object","default":{"light":"","dark":"","alt":""}},"search":{"type":"boolean","title":"Search Bar","description":"Hide or display the search bar.","default":true,"tags":["@studioInput boolean","@studioIcon i-mdi-magnify"],"id":"#appConfig/header/search"},"colorMode":{"type":"boolean","title":"Color Mode","description":"Hide or display the color mode button in your header.","default":true,"tags":["@studioInput boolean","@studioIcon i-mdi-moon-waning-crescent"],"id":"#appConfig/header/colorMode"},"links":{"type":"array","title":"Links","description":"Array of link object displayed in header.","default":[],"tags":["@studioInput array","@studioIcon i-mdi-link-variant"],"id":"#appConfig/header/links","items":{"type":"any"}}},"type":"object","default":{"logo":{"light":"","dark":"","alt":""},"search":true,"colorMode":true,"links":[]}},"footer":{"title":"Footer","description":"Footer configuration.","tags":["@studioIcon i-mdi-page-layout-footer"],"id":"#appConfig/footer","properties":{"credits":{"type":"string","title":"Footer credits section","description":"Text to display as credits in the footer.","default":"","tags":["@studioInput string","@studioIcon i-mdi-circle-edit-outline"],"id":"#appConfig/footer/credits"},"colorMode":{"type":"boolean","title":"Color Mode","description":"Hide or display the color mode button in the footer.","default":false,"tags":["@studioInput boolean","@studioIcon i-mdi-moon-waning-crescent"],"id":"#appConfig/footer/colorMode"},"links":{"type":"array","title":"Links","description":"Array of link object displayed in footer.","default":[],"tags":["@studioInput array","@studioIcon i-mdi-link-variant"],"id":"#appConfig/footer/links","items":{"type":"any"}}},"type":"object","default":{"credits":"","colorMode":false,"links":[]}},"toc":{"title":"Table of contents","description":"TOC configuration.","tags":["@studioIcon i-mdi-table-of-contents"],"id":"#appConfig/toc","properties":{"title":{"type":"string","title":"Title","description":"Text to display as title of the main toc.","default":"","tags":["@studioInput string","@studioIcon i-mdi-format-title"],"id":"#appConfig/toc/title"},"bottom":{"title":"Bottom","description":"Bottom TOC configuration.","tags":["@studioIcon i-mdi-table-of-contents"],"id":"#appConfig/toc/bottom","properties":{"title":{"type":"string","title":"Title","description":"Text to display as title of the bottom toc.","default":"","tags":["@studioInput string","@studioIcon i-mdi-format-title"],"id":"#appConfig/toc/bottom/title"},"edit":{"type":"string","title":"Edit Page Link","description":"URL of your repository content folder.","default":"","tags":["@studioInput string","@studioIcon i-ph-note-pencil"],"id":"#appConfig/toc/bottom/edit"},"links":{"type":"array","title":"Links","description":"Array of link object displayed in bottom toc.","default":[],"tags":["@studioInput array","@studioIcon i-mdi-link-variant"],"id":"#appConfig/toc/bottom/links","items":{"type":"any"}}},"type":"object","default":{"title":"","edit":"","links":[]}}},"type":"object","default":{"title":"","bottom":{"title":"","edit":"","links":[]}}}},"type":"object","default":{"nuxtIcon":{"size":"1em","class":"","aliases":{},"iconifyApiOptions":{"url":"https://api.iconify.design","publicApiFallback":false}},"ui":{"icons":{"search":"i-heroicons-magnifying-glass-20-solid","dark":"i-heroicons-moon-20-solid","light":"i-heroicons-sun-20-solid","external":"i-heroicons-arrow-up-right-20-solid","chevron":"i-heroicons-chevron-down-20-solid","hash":"i-heroicons-hashtag-20-solid"},"primary":"green","gray":"slate"},"seo":{"siteName":[]},"header":{"logo":{"light":"","dark":"","alt":""},"search":true,"colorMode":true,"links":[]},"footer":{"credits":"","colorMode":false,"links":[]},"toc":{"title":"","bottom":{"title":"","edit":"","links":[]}}}},"default":{"nuxtIcon":{"size":"1em","class":"","aliases":{},"iconifyApiOptions":{"url":"https://api.iconify.design","publicApiFallback":false}},"ui":{"icons":{"search":"i-heroicons-magnifying-glass-20-solid","dark":"i-heroicons-moon-20-solid","light":"i-heroicons-sun-20-solid","external":"i-heroicons-arrow-up-right-20-solid","chevron":"i-heroicons-chevron-down-20-solid","hash":"i-heroicons-hashtag-20-solid"},"primary":"green","gray":"slate"},"seo":{"siteName":[]},"header":{"logo":{"light":"","dark":"","alt":""},"search":true,"colorMode":true,"links":[]},"footer":{"credits":"","colorMode":false,"links":[]},"toc":{"title":"","bottom":{"title":"","edit":"","links":[]}}}},"appConfig":{"nuxt":{"buildId":"5db3ca28-2022-4e33-83ff-e967c9a32d3b"}},"content":{"sources":{},"ignores":[],"locales":[],"defaultLocale":"","highlight":false,"navigation":{"fields":[]},"documentDriven":false,"experimental":{"clientDB":false,"cacheContents":true,"stripQueryParameters":false,"advanceQuery":false,"search":""}},"components":[{"name":"DonationLink","path":"components/content/DonationLink.vue","meta":{"props":[{"name":"frequency","global":false,"description":"","tags":[],"required":false,"type":"any","declarations":[],"schema":"any"},{"name":"amount","global":false,"description":"","tags":[],"required":false,"type":"any","declarations":[],"schema":"any"}],"slots":[{"name":"default","type":"{ unwrap: string; }","description":"","declarations":[],"schema":{"kind":"object","type":"{ unwrap: string; }","schema":{"unwrap":{"name":"unwrap","global":false,"description":"","tags":[],"required":true,"type":"string","declarations":[],"schema":"string"}}}}],"events":[]}},{"name":"PressPatronButton","path":"components/content/PressPatronButton.vue","meta":{"props":[],"slots":[],"events":[]}},{"name":"ProseCode","path":"node_modules/@nuxt/content/dist/runtime/components/Prose/ProseCode.vue","meta":{"props":[{"name":"code","global":false,"description":"","tags":[],"required":false,"type":"string | undefined","declarations":[{"file":"/home/runner/work/wnews-nuxt/wnews-nuxt/node_modules/@nuxt/content/dist/runtime/components/Prose/ProseCode.vue","range":[76,121]}],"schema":{"kind":"enum","type":"string | undefined","schema":{"0":"undefined","1":"string"}},"default":"\"\""},{"name":"language","global":false,"description":"","tags":[],"required":false,"type":"string | undefined","declarations":[{"file":"/home/runner/work/wnews-nuxt/wnews-nuxt/node_modules/@nuxt/content/dist/runtime/components/Prose/ProseCode.vue","range":[125,176]}],"schema":{"kind":"enum","type":"string | undefined","schema":{"0":"undefined","1":"string"}},"default":"null"},{"name":"filename","global":false,"description":"","tags":[],"required":false,"type":"string | undefined","declarations":[{"file":"/home/runner/work/wnews-nuxt/wnews-nuxt/node_modules/@nuxt/content/dist/runtime/components/Prose/ProseCode.vue","range":[180,231]}],"schema":{"kind":"enum","type":"string | undefined","schema":{"0":"undefined","1":"string"}},"default":"null"},{"name":"highlights","global":false,"description":"","tags":[],"required":false,"type":"number[] | undefined","declarations":[{"file":"/home/runner/work/wnews-nuxt/wnews-nuxt/node_modules/@nuxt/content/dist/runtime/components/Prose/ProseCode.vue","range":[235,309]}],"schema":{"kind":"enum","type":"number[] | undefined","schema":{"0":"undefined","1":{"kind":"array","type":"number[]","schema":["number"]}}},"default":"[]"},{"name":"meta","global":false,"description":"","tags":[],"required":false,"type":"string | undefined","declarations":[{"file":"/home/runner/work/wnews-nuxt/wnews-nuxt/node_modules/@nuxt/content/dist/runtime/components/Prose/ProseCode.vue","range":[313,360]}],"schema":{"kind":"enum","type":"string | undefined","schema":{"0":"undefined","1":"string"}},"default":"null"}],"slots":[{"name":"default","type":"{}","description":"","declarations":[],"schema":{"kind":"object","type":"{}","schema":{}}}],"events":[]}},{"name":"ProseCodeInline","path":"node_modules/@nuxt/content/dist/runtime/components/Prose/ProseCodeInline.vue","meta":{"props":[],"slots":[{"name":"default","type":"{}","description":"","declarations":[],"schema":{"kind":"object","type":"{}","schema":{}}}],"events":[]}},{"name":"ProsePre","path":"node_modules/@nuxt/content/dist/runtime/components/Prose/ProsePre.vue","meta":{"props":[{"name":"code","global":false,"description":"","tags":[],"required":false,"type":"string | undefined","declarations":[{"file":"/home/runner/work/wnews-nuxt/wnews-nuxt/node_modules/@nuxt/content/dist/runtime/components/Prose/ProsePre.vue","range":[248,293]}],"schema":{"kind":"enum","type":"string | undefined","schema":{"0":"undefined","1":"string"}},"default":"\"\""},{"name":"language","global":false,"description":"","tags":[],"required":false,"type":"string | undefined","declarations":[{"file":"/home/runner/work/wnews-nuxt/wnews-nuxt/node_modules/@nuxt/content/dist/runtime/components/Prose/ProsePre.vue","range":[297,348]}],"schema":{"kind":"enum","type":"string | undefined","schema":{"0":"undefined","1":"string"}},"default":"null"},{"name":"filename","global":false,"description":"","tags":[],"required":false,"type":"string | undefined","declarations":[{"file":"/home/runner/work/wnews-nuxt/wnews-nuxt/node_modules/@nuxt/content/dist/runtime/components/Prose/ProsePre.vue","range":[352,403]}],"schema":{"kind":"enum","type":"string | undefined","schema":{"0":"undefined","1":"string"}},"default":"null"},{"name":"highlights","global":false,"description":"","tags":[],"required":false,"type":"number[] | undefined","declarations":[{"file":"/home/runner/work/wnews-nuxt/wnews-nuxt/node_modules/@nuxt/content/dist/runtime/components/Prose/ProsePre.vue","range":[407,481]}],"schema":{"kind":"enum","type":"number[] | undefined","schema":{"0":"undefined","1":{"kind":"array","type":"number[]","schema":["number"]}}},"default":"[]"},{"name":"meta","global":false,"description":"","tags":[],"required":false,"type":"string | undefined","declarations":[{"file":"/home/runner/work/wnews-nuxt/wnews-nuxt/node_modules/@nuxt/content/dist/runtime/components/Prose/ProsePre.vue","range":[485,532]}],"schema":{"kind":"enum","type":"string | undefined","schema":{"0":"undefined","1":"string"}},"default":"null"}],"slots":[{"name":"default","type":"{}","description":"","declarations":[],"schema":{"kind":"object","type":"{}","schema":{}}}],"events":[]}},{"name":"ProseA","path":"node_modules/@nuxtjs/mdc/dist/runtime/components/prose/ProseA.vue","meta":{"props":[{"name":"href","global":false,"description":"","tags":[],"required":false,"type":"string | undefined","declarations":[{"file":"/home/runner/work/wnews-nuxt/wnews-nuxt/node_modules/@nuxtjs/mdc/dist/runtime/components/prose/ProseA.vue","range":[146,191]}],"schema":{"kind":"enum","type":"string | undefined","schema":{"0":"undefined","1":"string"}},"default":"\"\""},{"name":"target","global":false,"description":"","tags":[],"required":false,"type":"string | undefined","declarations":[{"file":"/home/runner/work/wnews-nuxt/wnews-nuxt/node_modules/@nuxtjs/mdc/dist/runtime/components/prose/ProseA.vue","range":[195,270]}],"schema":{"kind":"enum","type":"string | undefined","schema":{"0":"undefined","1":"string"}},"default":"undefined"}],"slots":[{"name":"default","type":"{}","description":"","declarations":[],"schema":{"kind":"object","type":"{}","schema":{}}}],"events":[]}},{"name":"ProseBlockquote","path":"node_modules/@nuxtjs/mdc/dist/runtime/components/prose/ProseBlockquote.vue","meta":{"props":[],"slots":[{"name":"default","type":"{}","description":"","declarations":[],"schema":{"kind":"object","type":"{}","schema":{}}}],"events":[]}},{"name":"ProseEm","path":"node_modules/@nuxtjs/mdc/dist/runtime/components/prose/ProseEm.vue","meta":{"props":[],"slots":[{"name":"default","type":"{}","description":"","declarations":[],"schema":{"kind":"object","type":"{}","schema":{}}}],"events":[]}},{"name":"ProseH1","path":"node_modules/@nuxtjs/mdc/dist/runtime/components/prose/ProseH1.vue","meta":{"props":[{"name":"id","global":false,"description":"","tags":[],"required":false,"type":"string | undefined","declarations":[{"file":"/home/runner/work/wnews-nuxt/wnews-nuxt/node_modules/@nuxtjs/mdc/dist/runtime/components/prose/ProseH1.vue","range":[258,269]},{"file":"/home/runner/work/wnews-nuxt/wnews-nuxt/node_modules/@nuxtjs/mdc/dist/runtime/components/prose/ProseH1.vue","range":[258,269]}],"schema":{"kind":"enum","type":"string | undefined","schema":{"0":"undefined","1":"string"}}}],"slots":[{"name":"default","type":"{}","description":"","declarations":[],"schema":{"kind":"object","type":"{}","schema":{}}}],"events":[]}},{"name":"ProseH2","path":"node_modules/@nuxtjs/mdc/dist/runtime/components/prose/ProseH2.vue","meta":{"props":[{"name":"id","global":false,"description":"","tags":[],"required":false,"type":"string | undefined","declarations":[{"file":"/home/runner/work/wnews-nuxt/wnews-nuxt/node_modules/@nuxtjs/mdc/dist/runtime/components/prose/ProseH2.vue","range":[264,275]},{"file":"/home/runner/work/wnews-nuxt/wnews-nuxt/node_modules/@nuxtjs/mdc/dist/runtime/components/prose/ProseH2.vue","range":[264,275]}],"schema":{"kind":"enum","type":"string | undefined","schema":{"0":"undefined","1":"string"}}}],"slots":[{"name":"default","type":"{}","description":"","declarations":[],"schema":{"kind":"object","type":"{}","schema":{}}}],"events":[]}},{"name":"ProseH3","path":"node_modules/@nuxtjs/mdc/dist/runtime/components/prose/ProseH3.vue","meta":{"props":[{"name":"id","global":false,"description":"","tags":[],"required":false,"type":"string | undefined","declarations":[{"file":"/home/runner/work/wnews-nuxt/wnews-nuxt/node_modules/@nuxtjs/mdc/dist/runtime/components/prose/ProseH3.vue","range":[264,275]},{"file":"/home/runner/work/wnews-nuxt/wnews-nuxt/node_modules/@nuxtjs/mdc/dist/runtime/components/prose/ProseH3.vue","range":[264,275]}],"schema":{"kind":"enum","type":"string | undefined","schema":{"0":"undefined","1":"string"}}}],"slots":[{"name":"default","type":"{}","description":"","declarations":[],"schema":{"kind":"object","type":"{}","schema":{}}}],"events":[]}},{"name":"ProseH4","path":"node_modules/@nuxtjs/mdc/dist/runtime/components/prose/ProseH4.vue","meta":{"props":[{"name":"id","global":false,"description":"","tags":[],"required":false,"type":"string | undefined","declarations":[{"file":"/home/runner/work/wnews-nuxt/wnews-nuxt/node_modules/@nuxtjs/mdc/dist/runtime/components/prose/ProseH4.vue","range":[264,275]},{"file":"/home/runner/work/wnews-nuxt/wnews-nuxt/node_modules/@nuxtjs/mdc/dist/runtime/components/prose/ProseH4.vue","range":[264,275]}],"schema":{"kind":"enum","type":"string | undefined","schema":{"0":"undefined","1":"string"}}}],"slots":[{"name":"default","type":"{}","description":"","declarations":[],"schema":{"kind":"object","type":"{}","schema":{}}}],"events":[]}},{"name":"ProseH5","path":"node_modules/@nuxtjs/mdc/dist/runtime/components/prose/ProseH5.vue","meta":{"props":[{"name":"id","global":false,"description":"","tags":[],"required":false,"type":"string | undefined","declarations":[{"file":"/home/runner/work/wnews-nuxt/wnews-nuxt/node_modules/@nuxtjs/mdc/dist/runtime/components/prose/ProseH5.vue","range":[264,275]},{"file":"/home/runner/work/wnews-nuxt/wnews-nuxt/node_modules/@nuxtjs/mdc/dist/runtime/components/prose/ProseH5.vue","range":[264,275]}],"schema":{"kind":"enum","type":"string | undefined","schema":{"0":"undefined","1":"string"}}}],"slots":[{"name":"default","type":"{}","description":"","declarations":[],"schema":{"kind":"object","type":"{}","schema":{}}}],"events":[]}},{"name":"ProseH6","path":"node_modules/@nuxtjs/mdc/dist/runtime/components/prose/ProseH6.vue","meta":{"props":[{"name":"id","global":false,"description":"","tags":[],"required":false,"type":"string | undefined","declarations":[{"file":"/home/runner/work/wnews-nuxt/wnews-nuxt/node_modules/@nuxtjs/mdc/dist/runtime/components/prose/ProseH6.vue","range":[264,275]},{"file":"/home/runner/work/wnews-nuxt/wnews-nuxt/node_modules/@nuxtjs/mdc/dist/runtime/components/prose/ProseH6.vue","range":[264,275]}],"schema":{"kind":"enum","type":"string | undefined","schema":{"0":"undefined","1":"string"}}}],"slots":[{"name":"default","type":"{}","description":"","declarations":[],"schema":{"kind":"object","type":"{}","schema":{}}}],"events":[]}},{"name":"ProseHr","path":"node_modules/@nuxtjs/mdc/dist/runtime/components/prose/ProseHr.vue","meta":{"props":[],"slots":[],"events":[]}},{"name":"ProseImg","path":"node_modules/@nuxtjs/mdc/dist/runtime/components/prose/ProseImg.vue","meta":{"props":[{"name":"src","global":false,"description":"","tags":[],"required":false,"type":"string | undefined","declarations":[{"file":"/home/runner/work/wnews-nuxt/wnews-nuxt/node_modules/@nuxtjs/mdc/dist/runtime/components/prose/ProseImg.vue","range":[289,333]}],"schema":{"kind":"enum","type":"string | undefined","schema":{"0":"undefined","1":"string"}},"default":"\"\""},{"name":"alt","global":false,"description":"","tags":[],"required":false,"type":"string | undefined","declarations":[{"file":"/home/runner/work/wnews-nuxt/wnews-nuxt/node_modules/@nuxtjs/mdc/dist/runtime/components/prose/ProseImg.vue","range":[337,381]}],"schema":{"kind":"enum","type":"string | undefined","schema":{"0":"undefined","1":"string"}},"default":"\"\""},{"name":"width","global":false,"description":"","tags":[],"required":false,"type":"string | number | undefined","declarations":[{"file":"/home/runner/work/wnews-nuxt/wnews-nuxt/node_modules/@nuxtjs/mdc/dist/runtime/components/prose/ProseImg.vue","range":[385,448]}],"schema":{"kind":"enum","type":"string | number | undefined","schema":{"0":"undefined","1":"string","2":"number"}},"default":"undefined"},{"name":"height","global":false,"description":"","tags":[],"required":false,"type":"string | number | undefined","declarations":[{"file":"/home/runner/work/wnews-nuxt/wnews-nuxt/node_modules/@nuxtjs/mdc/dist/runtime/components/prose/ProseImg.vue","range":[452,516]}],"schema":{"kind":"enum","type":"string | number | undefined","schema":{"0":"undefined","1":"string","2":"number"}},"default":"undefined"}],"slots":[],"events":[]}},{"name":"ProseLi","path":"node_modules/@nuxtjs/mdc/dist/runtime/components/prose/ProseLi.vue","meta":{"props":[],"slots":[{"name":"default","type":"{}","description":"","declarations":[],"schema":{"kind":"object","type":"{}","schema":{}}}],"events":[]}},{"name":"ProseOl","path":"node_modules/@nuxtjs/mdc/dist/runtime/components/prose/ProseOl.vue","meta":{"props":[],"slots":[{"name":"default","type":"{}","description":"","declarations":[],"schema":{"kind":"object","type":"{}","schema":{}}}],"events":[]}},{"name":"ProseP","path":"node_modules/@nuxtjs/mdc/dist/runtime/components/prose/ProseP.vue","meta":{"props":[],"slots":[{"name":"default","type":"{}","description":"","declarations":[],"schema":{"kind":"object","type":"{}","schema":{}}}],"events":[]}},{"name":"ProseScript","path":"node_modules/@nuxtjs/mdc/dist/runtime/components/prose/ProseScript.vue","meta":{"props":[{"name":"src","global":false,"description":"","tags":[],"required":false,"type":"string | undefined","declarations":[{"file":"/home/runner/work/wnews-nuxt/wnews-nuxt/node_modules/@nuxtjs/mdc/dist/runtime/components/prose/ProseScript.vue","range":[317,361]}],"schema":{"kind":"enum","type":"string | undefined","schema":{"0":"undefined","1":"string"}},"default":"\"\""}],"slots":[],"events":[]}},{"name":"ProseStrong","path":"node_modules/@nuxtjs/mdc/dist/runtime/components/prose/ProseStrong.vue","meta":{"props":[],"slots":[{"name":"default","type":"{}","description":"","declarations":[],"schema":{"kind":"object","type":"{}","schema":{}}}],"events":[]}},{"name":"ProseTable","path":"node_modules/@nuxtjs/mdc/dist/runtime/components/prose/ProseTable.vue","meta":{"props":[],"slots":[{"name":"default","type":"{}","description":"","declarations":[],"schema":{"kind":"object","type":"{}","schema":{}}}],"events":[]}},{"name":"ProseTbody","path":"node_modules/@nuxtjs/mdc/dist/runtime/components/prose/ProseTbody.vue","meta":{"props":[],"slots":[{"name":"default","type":"{}","description":"","declarations":[],"schema":{"kind":"object","type":"{}","schema":{}}}],"events":[]}},{"name":"ProseTd","path":"node_modules/@nuxtjs/mdc/dist/runtime/components/prose/ProseTd.vue","meta":{"props":[],"slots":[{"name":"default","type":"{}","description":"","declarations":[],"schema":{"kind":"object","type":"{}","schema":{}}}],"events":[]}},{"name":"ProseTh","path":"node_modules/@nuxtjs/mdc/dist/runtime/components/prose/ProseTh.vue","meta":{"props":[],"slots":[{"name":"default","type":"{}","description":"","declarations":[],"schema":{"kind":"object","type":"{}","schema":{}}}],"events":[]}},{"name":"ProseThead","path":"node_modules/@nuxtjs/mdc/dist/runtime/components/prose/ProseThead.vue","meta":{"props":[],"slots":[{"name":"default","type":"{}","description":"","declarations":[],"schema":{"kind":"object","type":"{}","schema":{}}}],"events":[]}},{"name":"ProseTr","path":"node_modules/@nuxtjs/mdc/dist/runtime/components/prose/ProseTr.vue","meta":{"props":[],"slots":[{"name":"default","type":"{}","description":"","declarations":[],"schema":{"kind":"object","type":"{}","schema":{}}}],"events":[]}},{"name":"ProseUl","path":"node_modules/@nuxtjs/mdc/dist/runtime/components/prose/ProseUl.vue","meta":{"props":[],"slots":[{"name":"default","type":"{}","description":"","declarations":[],"schema":{"kind":"object","type":"{}","schema":{}}}],"events":[]}},{"name":"Icon","path":"node_modules/nuxt-icon/dist/runtime/Icon.vue","meta":{"props":[{"name":"name","global":false,"description":"","tags":[],"required":true,"type":"string","declarations":[{"file":"/home/runner/work/wnews-nuxt/wnews-nuxt/node_modules/nuxt-icon/dist/runtime/Icon.vue","range":[669,717]},{"file":"/home/runner/work/wnews-nuxt/wnews-nuxt/node_modules/nuxt-icon/dist/runtime/Icon.vue","range":[669,717]}],"schema":"string"},{"name":"size","global":false,"description":"","tags":[],"required":false,"type":"string | undefined","declarations":[{"file":"/home/runner/work/wnews-nuxt/wnews-nuxt/node_modules/nuxt-icon/dist/runtime/Icon.vue","range":[721,766]}],"schema":{"kind":"enum","type":"string | undefined","schema":{"0":"undefined","1":"string"}},"default":"\"\""}],"slots":[{"name":"default","type":"{}","description":"","declarations":[],"schema":{"kind":"object","type":"{}","schema":{}}}],"events":[]}},{"name":"IconCSS","path":"node_modules/nuxt-icon/dist/runtime/IconCSS.vue","meta":{"props":[{"name":"name","global":false,"description":"","tags":[],"required":true,"type":"string","declarations":[{"file":"/home/runner/work/wnews-nuxt/wnews-nuxt/node_modules/nuxt-icon/dist/runtime/IconCSS.vue","range":[387,435]},{"file":"/home/runner/work/wnews-nuxt/wnews-nuxt/node_modules/nuxt-icon/dist/runtime/IconCSS.vue","range":[387,435]}],"schema":"string"},{"name":"size","global":false,"description":"","tags":[],"required":false,"type":"string | undefined","declarations":[{"file":"/home/runner/work/wnews-nuxt/wnews-nuxt/node_modules/nuxt-icon/dist/runtime/IconCSS.vue","range":[439,484]}],"schema":{"kind":"enum","type":"string | undefined","schema":{"0":"undefined","1":"string"}},"default":"\"\""}],"slots":[],"events":[]}}]}