{"id":"df830ea2-0871-4282-86ef-61ec2dc0a97f","timestamp":1711693390358,"matcher":{"static":{},"wildcard":{},"dynamic":{}},"prerendered":["/firstpeoples","/immigration","/","/articles","/gardening","/advertisements","/history","/recipes","/past-issues","/wildlife","/past-issues/2024","/contact","/about","/advertise","/subscribe","/articles/2024/easter-in-rushworth","/gardening/2024/2024-03-28","/advertisements/helen-truran-celebrant","/advertisements/ky-funeral-services","/advertisements/lipshut-law","/advertisements/morgan-fuel","/advertisements/perrys-butchery","/advertisements/rexterminate","/advertisements/rushworth-variety","/history/2024/2024-03-28","/recipes/2024/2024-03-28","/past-issues/2024/2024-02-01","/past-issues/2024/2024-02-15","/past-issues/2024/2024-02-29","/past-issues/2024/2024-03-14","/past-issues/2024/2024-03-28","/past-issues/2024/2024-04-11","/past-issues/2024/2024-04-25","/past-issues/2024/2024-05-09","/past-issues/2024/2024-05-23","/past-issues/2024/2024-06-06","/past-issues/2024/2024-06-20","/wildlife/2024/2024-03-28"]}